slidie_ttyd/__init__.py
slidie_ttyd/runner.py
slidie_ttyd/script_generators.py
slidie_ttyd/server.py
slidie_ttyd-0.0.1.dist-info/LICENCE
slidie_ttyd-0.0.1.dist-info/METADATA
slidie_ttyd-0.0.1.dist-info/WHEEL
slidie_ttyd-0.0.1.dist-info/entry_points.txt
slidie_ttyd-0.0.1.dist-info/top_level.txt
slidie_ttyd-0.0.1.dist-info/RECORD
