Metadata-Version: 2.1
Name: slidie-ttyd
Version: 0.0.1
License: GNU GENERAL PUBLIC LICENSE
License-File: LICENCE
Requires-Dist: aiohttp
